tf_titans/__init__.py
tf_titans/attention.py
tf_titans/memory.py
tf_titans/titans.py
tf_titans/train.py
tf_titans-0.1.3.dist-info/LICENSE
tf_titans-0.1.3.dist-info/METADATA
tf_titans-0.1.3.dist-info/WHEEL
tf_titans-0.1.3.dist-info/top_level.txt
tf_titans-0.1.3.dist-info/RECORD
