Metadata-Version: 2.2
Name: tf-titans
Version: 0.1.3
Summary: A custom implementation of titans architecture.
Home-page: https://github.com/Mohammed-Saajid/tf-titans
Author: Mohammed Saajid
Author-email: Mohammed Saajid <mohammedsaajid23@gmail.com>
License: MIT
Project-URL: Homepage, https://pypi.org/project/tf-titans/
Project-URL: Repository, https://github.com/Mohammed-Saajid/tf-titans
Classifier: Programming Language :: Python :: 3
Classifier: License :: OSI Approved :: MIT License
Classifier: Operating System :: OS Independent
Classifier: Topic :: Scientific/Engineering :: Artificial Intelligence
Requires-Python: >=3.9
License-File: LICENSE
Requires-Dist: tensorflow>=2.11.0
Dynamic: author
Dynamic: home-page
Dynamic: requires-python
